<?xml version='1.0' encoding='UTF-8' standalone='yes' ?><hierarchy rotation="0"><node index="0" text="" resource-id="" class="android.widget.FrameLayout" package="com.aigymmentor.app" content-desc="" checkable="false" checked="false" clickable="false" enabled="true" focusable="false" focused="false" scrollable="false" long-clickable="false" password="false" selected="false" bounds="[0,0][1440,3088]" drawing-order="0" hint=""><node index="0" text="" resource-id="" class="android.widget.LinearLayout" package="com.aigymmentor.app" content-desc="" checkable="false" checked="false" clickable="false" enabled="true" focusable="false" focused="false" scrollable="false" long-clickable="false" password="false" selected="false" bounds="[0,0][1440,3088]" drawing-order="1" hint=""><node index="0" text="" resource-id="android:id/content" class="android.widget.FrameLayout" package="com.aigymmentor.app" content-desc="" checkable="false" checked="false" clickable="false" enabled="true" focusable="false" focused="false" scrollable="false" long-clickable="false" password="false" selected="false" bounds="[0,0][1440,3088]" drawing-order="2" hint=""><node index="0" text="" resource-id="" class="android.widget.FrameLayout" package="com.aigymmentor.app" content-desc="" checkable="false" checked="false" clickable="false" enabled="true" focusable="true" focused="false" scrollable="false" long-clickable="false" password="false" selected="false" bounds="[0,0][1440,3088]" drawing-order="1" hint=""><node index="0" text="" resource-id="" class="android.view.View" package="com.aigymmentor.app" content-desc="" checkable="false" checked="false" clickable="false" enabled="true" focusable="false" focused="false" scrollable="false" long-clickable="false" password="false" selected="false" bounds="[0,0][1440,3088]" drawing-order="0" hint=""><node index="0" text="" resource-id="" class="android.view.View" package="com.aigymmentor.app" content-desc="Dismiss" checkable="false" checked="false" clickable="true" enabled="true" focusable="true" focused="false" scrollable="false" long-clickable="false" password="false" selected="false" bounds="[0,0][1440,3088]" drawing-order="0" hint=""><node index="0" text="" resource-id="" class="android.view.View" package="com.aigymmentor.app" content-desc="" checkable="false" checked="false" clickable="false" enabled="true" focusable="false" focused="false" scrollable="false" long-clickable="false" password="false" selected="false" bounds="[0,0][1440,3088]" drawing-order="0" hint=""><node index="0" text="" resource-id="" class="android.view.View" package="com.aigymmentor.app" content-desc="" checkable="false" checked="false" clickable="false" enabled="true" focusable="false" focused="false" scrollable="false" long-clickable="false" password="false" selected="false" bounds="[0,0][1440,3088]" drawing-order="0" hint=""><node index="0" text="" resource-id="" class="android.view.View" package="com.aigymmentor.app" content-desc="" checkable="false" checked="false" clickable="false" enabled="true" focusable="false" focused="false" scrollable="false" long-clickable="false" password="false" selected="false" bounds="[0,100][1440,3088]" drawing-order="0" hint=""><node index="0" text="" resource-id="" class="android.view.View" package="com.aigymmentor.app" content-desc="" checkable="false" checked="false" clickable="false" enabled="true" focusable="false" focused="false" scrollable="false" long-clickable="false" password="false" selected="false" bounds="[140,1125][1300,2063]" drawing-order="0" hint=""><node index="0" text="" resource-id="" class="android.view.View" package="com.aigymmentor.app" content-desc="Debug Info" checkable="false" checked="false" clickable="false" enabled="true" focusable="true" focused="false" scrollable="false" long-clickable="false" password="false" selected="false" bounds="[224,1209][1216,1321]" drawing-order="0" hint="" /><node index="1" text="" resource-id="" class="android.view.View" package="com.aigymmentor.app" content-desc="" checkable="false" checked="false" clickable="false" enabled="true" focusable="false" focused="false" scrollable="false" long-clickable="false" password="false" selected="false" bounds="[224,1377][1216,1727]" drawing-order="0" hint=""><node index="0" text="" resource-id="" class="android.view.View" package="com.aigymmentor.app" content-desc="Templates: 5&#10;Exercises: 171&#10;&#10;Latest Template: Rahul — 6-Day Push Pull Legs Warrior Program" checkable="false" checked="false" clickable="false" enabled="true" focusable="true" focused="false" scrollable="false" long-clickable="false" password="false" selected="false" bounds="[224,1377][1216,1727]" drawing-order="0" hint="" /></node><node index="2" text="" resource-id="" class="android.widget.Button" package="com.aigymmentor.app" content-desc="OK" checkable="false" checked="false" clickable="true" enabled="true" focusable="true" focused="false" scrollable="false" long-clickable="false" password="false" selected="false" bounds="[992,1811][1216,1979]" drawing-order="0" hint="" /></node></node></node></node></node></node></node></node></node></node></hierarchy>